chiakilisp/__init__.py
chiakilisp/lexer.py
chiakilisp/parser.py
chiakilisp/runtime.py
chiakilisp/spec.py
chiakilisp/utils.py
chiakilisp/corelib/core.cl
chiakilisp/models/__init__.py
chiakilisp/models/expression.py
chiakilisp/models/forward.py
chiakilisp/models/literal.py
chiakilisp/models/token.py
chiakilisp/proxies/__init__.py
chiakilisp/proxies/keyword.py
chiakilisp-1.3.0.data/scripts/chiakilang
chiakilisp-1.3.0.dist-info/METADATA
chiakilisp-1.3.0.dist-info/WHEEL
chiakilisp-1.3.0.dist-info/top_level.txt
chiakilisp-1.3.0.dist-info/RECORD
