Metadata-Version: 2.1
Name: chiakilisp
Version: 1.3.0
Summary: ChiakiLisp - Yet another LISP
Home-page: https://chiakilisp.jedi2light.moe
Author: @jedi2light
Author-email: jedi2light@jedi2light.moe
Maintainer: @jedi2light
Maintainer-email: jedi2light@jedi2light.moe
License: GNU GPL v2
Project-URL: Web Site, https://chiakilisp.jedi2light.moe
Project-URL: Source, https://gitlab.com/jedi2light/chiakilisp.git/
Project-URL: Bug Tracker, https://gitlab.com/jedi2light/chiakilisp/issues
Classifier: Programming Language :: Python :: 3
Classifier: Operating System :: OS Independent
Requires-Python: >=3.6
Requires-Dist: hashedcolls (==1.1.0)
